squeaky/__init__.py
squeaky/tools.py
squeaky/passes/cell_ids.py
squeaky/passes/empty_cells.py
squeaky/passes/execution_count.py
squeaky/passes/metadata.py
squeaky/passes/outputs.py
squeaky/passes/svg.py
squeaky/passes/svg_id.py
squeaky/passes/trailing_whitespace.py
squeaky-0.7.0.dist-info/METADATA
squeaky-0.7.0.dist-info/WHEEL
squeaky-0.7.0.dist-info/entry_points.txt
squeaky-0.7.0.dist-info/licenses/LICENSE
squeaky-0.7.0.dist-info/RECORD
