Metadata-Version: 2.1
Name: squeaky
Version: 0.7.0
Summary: Remove noise from notebooks for cleaner version control diffs
Project-URL: Homepage, https://github.com/frankharkins/squeaky-nb
Project-URL: Bug Tracker, https://github.com/frankharkins/squeaky-nb/issues
Author-email: Frank Harkins <frankharkins@hotmail.co.uk>
License-Expression: Apache-2.0
License-File: LICENSE
Requires-Python: >=3.7
Requires-Dist: nbformat
Requires-Dist: scour
